sparktorch/__init__.py
sparktorch/distributed.py
sparktorch/early_stopper.py
sparktorch/hogwild.py
sparktorch/inference.py
sparktorch/pipeline_util.py
sparktorch/rw_lock.py
sparktorch/server.py
sparktorch/torch_distributed.py
sparktorch/util.py
sparktorch/tests/__init__.py
sparktorch/tests/simple_net.py
sparktorch/tests/test_sparktorch.py
sparktorch-0.2.0.dist-info/LICENSE
sparktorch-0.2.0.dist-info/METADATA
sparktorch-0.2.0.dist-info/WHEEL
sparktorch-0.2.0.dist-info/top_level.txt
sparktorch-0.2.0.dist-info/RECORD
