Metadata-Version: 2.1
Name: sparktorch
Version: 0.2.0
Summary: Distributed training of PyTorch networks on Apache Spark with ML Pipeline support
Home-page: https://github.com/dmmiller612/sparktorch
Download-URL: https://github.com/dmmiller612/sparktorch/archive/0.2.0.tar.gz
Author: Derek Miller
Author-email: dmmiller612@gmail.com
License: MIT
Keywords: pytorch,spark,sparktorch,machine learning,deep learning
License-File: LICENSE
Requires-Dist: torch
Requires-Dist: flask
Requires-Dist: requests
Requires-Dist: dill
